jaxex/__init__.py
jaxex/config.py
jaxex/experiment.py
jaxex/jax_wrapper.py
jaxex/model.py
jaxex/registry.py
jaxex/settings.py
jaxex/tensor_net_experiment.py
jaxex/torch_wrapper.py
jaxex/visualizations.py
jaxex-0.0.3.dist-info/LICENSE
jaxex-0.0.3.dist-info/WHEEL
jaxex-0.0.3.dist-info/METADATA
jaxex-0.0.3.dist-info/RECORD
